Flagger/__init__.py
Trueflagger2-0.1.2.dist-info/LICENSE
Trueflagger2-0.1.2.dist-info/METADATA
Trueflagger2-0.1.2.dist-info/WHEEL
Trueflagger2-0.1.2.dist-info/top_level.txt
Trueflagger2-0.1.2.dist-info/RECORD
