Metadata-Version: 2.1
Name: Trueflagger2
Version: 0.1.2
Summary: Uma biblioteca simples para criação e controle de flags por arquivos.
Author: Leonardo Nery
Author-email: leonardonery616@gmail.com
Classifier: Programming Language :: Python :: 3
Classifier: Intended Audience :: Developers
Classifier: License :: OSI Approved :: MIT License
Classifier: Operating System :: OS Independent
Requires-Python: >=3.6
License-File: LICENSE
